{
  "unversionedId": "animations",
  "id": "animations",
  "title": "Animations",
  "description": "Some of these mods can affect game balance by differing from vanilla attack speed and reload",
  "source": "@site/guide/animations.md",
  "sourceDirName": ".",
  "slug": "/animations",
  "permalink": "/wastelandsurvivalguide/guide/animations",
  "draft": false,
  "tags": [],
  "version": "current",
  "frontMatter": {},
  "sidebar": "sidebar",
  "previous": {
    "title": "Visuals",
    "permalink": "/wastelandsurvivalguide/guide/visuals"
  },
  "next": {
    "title": "Final Steps",
    "permalink": "/wastelandsurvivalguide/guide/finish"
  }
}